[{"name":"include","trans":["incl"]},{"name":"iostream","trans":["Input/output header files"]},{"name":"using","trans":["utilized"]},{"name":"namespace","trans":["namespace"]},{"name":"std","trans":["Standard abbreviations"]},{"name":"main","trans":["main function"]},{"name":"int","trans":["Declaring an integer variable or function"]},{"name":"char","trans":["Declaring a character variable or function"]},{"name":"double","trans":["Declaring a double precision variable or function"]},{"name":"float","trans":["Declaring a floating-point variable or function"]},{"name":"long","trans":["Declaring a long integer variable or function"]},{"name":"short","trans":["Declaring a short integer variable or function"]},{"name":"signed","trans":["Declaring a signed type variable or function"]},{"name":"unsigned","trans":["Declaring an unsigned type variable or function"]},{"name":"enum","trans":["Declaring an enumeration type"]},{"name":"struct","trans":["Declaring a structure variable or function"]},{"name":"union","trans":["Declaring a common (federated) data type"]},{"name":"cin","trans":["Enter the command"]},{"name":"cout","trans":["output command"]},{"name":"endl","trans":["An abbreviation for end line, line break"]},{"name":"scanf","trans":["Enter the command"]},{"name":"printf","trans":["output command"]},{"name":"void","trans":["Declare that a function has no return value or no parameters, and declare an untyped pointer"]},{"name":"for","trans":["A looping statement"]},{"name":"do","trans":["The loop body of a looping statement"]},{"name":"while","trans":["Cyclic conditions for looping statements"]},{"name":"break","trans":["Break out of the current loop"]},{"name":"continue","trans":["End the current cycle and start the next cycle"]},{"name":"if","trans":["conditional statements"]},{"name":"else","trans":["Conditional statements negate branches (used in conjunction with if)"]},{"name":"goto","trans":["unconditional jump statement"]},{"name":"switch","trans":["Used for switch statements"]},{"name":"case","trans":["Switch statement branch"]},{"name":"default","trans":["The “other” branch in switch statements"]},{"name":"return","trans":["Subroutine return statement (can be with parameters or without parameters)"]},{"name":"static","trans":["Declaring static variables"]},{"name":"const","trans":["Declaring a read-only variable (*note it's a variable*)"]},{"name":"sizeof","trans":["Compute data type length"]},{"name":"typedef","trans":["Used to alias data types (of course it has other uses)"]}]